your_package/__init__.py
your_package/module.py
passwordgenby-1.0.0.dist-info/METADATA
passwordgenby-1.0.0.dist-info/WHEEL
passwordgenby-1.0.0.dist-info/top_level.txt
passwordgenby-1.0.0.dist-info/RECORD
