Metadata-Version: 2.1
Name: passwordgenby
Version: 1.0.0
Summary: generates password
Author: kanchan
Author-email: your-email@example.com
Requires-Dist: dependency1
Requires-Dist: dependency2
